pawnlib/__init__.py
pawnlib/__main__.py
pawnlib/__version__.py
pawnlib/asyncio/__init__.py
pawnlib/asyncio/async_helper.py
pawnlib/asyncio/run.py
pawnlib/blockchain/__init__.py
pawnlib/blockchain/utils.py
pawnlib/blockchain/goloop/__init__.py
pawnlib/blockchain/goloop/info.py
pawnlib/blockchain/goloop/models.py
pawnlib/blockchain/goloop/monitor.py
pawnlib/blockchain/goloop/p2p.py
pawnlib/builder/__init__.py
pawnlib/builder/generator.py
pawnlib/builder/templates/__init__.py
pawnlib/builder/templates/app_with_logging.tmpl
pawnlib/cli/__init__.py
pawnlib/cli/aws.py
pawnlib/cli/banner.py
pawnlib/cli/compose.py
pawnlib/cli/docker.py
pawnlib/cli/goloop.py
pawnlib/cli/gs.py
pawnlib/cli/http.py
pawnlib/cli/icon.py
pawnlib/cli/info.py
pawnlib/cli/init.py
pawnlib/cli/inspect.py
pawnlib/cli/main_cli.py
pawnlib/cli/main_cli_with_required.py__
pawnlib/cli/metadata.py
pawnlib/cli/mon.py
pawnlib/cli/net.py
pawnlib/cli/noti.py
pawnlib/cli/pawns_cli.py__
pawnlib/cli/proxy.py
pawnlib/cli/rpc.py
pawnlib/cli/s3.py
pawnlib/cli/s3_old.py
pawnlib/cli/scan_key.py
pawnlib/cli/server.py
pawnlib/cli/snap.py
pawnlib/cli/tf.py
pawnlib/cli/top.py
pawnlib/cli/wallet.py
pawnlib/cli/websocket.py
pawnlib/cli/templates/__init__.py
pawnlib/cli/templates/docker_echo.tmpl
pawnlib/cli/templates/docker_planet.tmpl
pawnlib/config/__fix_import.py
pawnlib/config/__init__.py
pawnlib/config/configure.py
pawnlib/config/console.py
pawnlib/config/first_run_checker.py
pawnlib/config/globalconfig.py
pawnlib/config/globalconfig_legacy.py
pawnlib/config/improved_globalconfig.py
pawnlib/config/logging_config.py
pawnlib/config/settings_config.py
pawnlib/docker/__init__.py
pawnlib/docker/async_docker.py
pawnlib/docker/compose.py
pawnlib/exceptions/__init__.py
pawnlib/exceptions/notifier.py
pawnlib/input/__init__.py
pawnlib/input/prompt.py
pawnlib/metrics/__init__.py
pawnlib/metrics/tracker.py
pawnlib/models/__init__.py
pawnlib/models/response.py
pawnlib/output/__init__.py
pawnlib/output/color_print.py
pawnlib-2.1.43.dist-info/METADATA
pawnlib-2.1.43.dist-info/WHEEL
pawnlib-2.1.43.dist-info/entry_points.txt
pawnlib-2.1.43.dist-info/RECORD
