Metadata-Version: 2.4
Name: pawnlib
Version: 2.1.43
Summary: pawnlib: A versatile Python library for Infrastructure as Code (IaC), offering tools for SSH monitoring, WebSocket connections, and more.
Project-URL: Changelog, https://github.com/jinwoo-j/pawnlib
Project-URL: Documentation, https://pawnlib.readthedocs.io
Project-URL: Homepage, https://pawnlib.readthedocs.io
Project-URL: Source, https://github.com/jinwoo-j/pawnlib
Author-email: Jinwoo <jinwoo@parametacorp.com>
License: MIT License
Keywords: Python IaC,SSH monitoring Python,pawnlib tools
Classifier: Development Status :: 4 - Beta
Classifier: Environment :: Plugins
Classifier: Intended Audience :: Developers
Classifier: License :: OSI Approved :: MIT License
Classifier: Operating System :: OS Independent
Classifier: Programming Language :: Python :: 3
Classifier: Programming Language :: Python :: 3 :: Only
Classifier: Programming Language :: Python :: 3.7
Classifier: Programming Language :: Python :: 3.8
Classifier: Programming Language :: Python :: 3.9
Classifier: Programming Language :: Python :: 3.10
Classifier: Programming Language :: Python :: 3.11
Classifier: Topic :: Internet :: WWW/HTTP
Classifier: Topic :: Software Development :: Libraries :: Python Modules
Classifier: Topic :: System :: Monitoring
Requires-Python: >=3.7
Requires-Dist: aiofiles>=22.1.0
Requires-Dist: aiohttp>=3.8.6
Requires-Dist: aiometer>=0.3.0
Requires-Dist: argparse>=1.4.0
Requires-Dist: asttokens>=2.0.5
Requires-Dist: asyncio>=3.4.3
Requires-Dist: certifi>=2020.12.15
Requires-Dist: charset-normalizer>=2.1.0
Requires-Dist: deprecated~=1.2.13
Requires-Dist: devtools>=0.8.0
Requires-Dist: dnspython~=2.7.0
Requires-Dist: executing>=0.8.3
Requires-Dist: httpx~=0.25.0
Requires-Dist: idna>=2.5
Requires-Dist: inquirerpy==0.3.4
Requires-Dist: jinja2>=3.0.3
Requires-Dist: parameterized>=0.8.1
Requires-Dist: psutil~=5.9.8
Requires-Dist: pyfiglet>=0.8.post1
Requires-Dist: pygments>=2.14.0
Requires-Dist: python-dotenv~=0.21.1
Requires-Dist: pyyaml>=5.3.1
Requires-Dist: requests>=2.25.0
Requires-Dist: rich>=12.0.1
Requires-Dist: six>=1.15.0
Requires-Dist: tabulate>=0.8.7
Requires-Dist: termcolor>=1.1.0
Requires-Dist: tqdm~=4.65.0
Requires-Dist: urllib3~=1.26.0
Requires-Dist: websocket-client>=0.59.0
Provides-Extra: brotli
Requires-Dist: brotli; (platform_python_implementation == 'CPython') and extra == 'brotli'
Requires-Dist: brotlicffi; (platform_python_implementation != 'CPython') and extra == 'brotli'
Provides-Extra: docker
Requires-Dist: aiodocker~=0.21.0; extra == 'docker'
Provides-Extra: full
Requires-Dist: aioboto3~=11.3.1; extra == 'full'
Requires-Dist: aiodocker~=0.21.0; extra == 'full'
Requires-Dist: boto3>=1.28.3; extra == 'full'
Requires-Dist: coincurve~=18.0.0; extra == 'full'
Requires-Dist: eth-keyfile>=0.6.1; extra == 'full'
Requires-Dist: redis~=4.5.1; extra == 'full'
Requires-Dist: rich<14,>=10; extra == 'full'
Requires-Dist: xxhash~=3.5.0; extra == 'full'
Provides-Extra: wallet
Requires-Dist: coincurve~=18.0.0; extra == 'wallet'
Requires-Dist: eth-keyfile>=0.6.1; extra == 'wallet'
Requires-Dist: rich<14,>=10; extra == 'wallet'
